renaminator/__init__.py
renaminator/__main__.py
renaminator/filer.py
renaminator-0.1.0.dist-info/entry_points.txt
renaminator-0.1.0.dist-info/WHEEL
renaminator-0.1.0.dist-info/METADATA
renaminator-0.1.0.dist-info/RECORD
